setup.py
invoice_to_pdf_generator.egg-info/PKG-INFO
invoice_to_pdf_generator.egg-info/SOURCES.txt
invoice_to_pdf_generator.egg-info/dependency_links.txt
invoice_to_pdf_generator.egg-info/requires.txt
invoice_to_pdf_generator.egg-info/top_level.txt
invoicing/__init__.py
invoicing/invoice.py